Metadata-Version: 2.1
Name: mailupdater
Version: 0.0.3
Summary: Easily send mail updates to yourself.
Home-page: https://github.com/ychnlgy/MailUpdater
Author: Yuchen Li
Author-email: ychnlgy@gmail.com
License: MIT
Platform: UNKNOWN
